[
  {
    "id": "a-sherwyn-fawwaz-nitisara-suthaputra",
    "namaLengkap": "A. Sherwyn Fawwaz Nitisara Suthaputra",
    "jurusan": "Sistem Informasi"
  },
  {
    "id": "abby-shelley-tampubolon",
    "namaLengkap": "Abby Shelley Tampubolon",
    "jurusan": "Sistem Informasi"
  },
  {
    "id": "abdul-zacky",
    "namaLengkap": "Abdul Zacky",
    "jurusan": "Sistem Informasi"
  },
  {
    "id": "abella-maya-santi",
    "namaLengkap": "Abella Maya Santi",
    "jurusan": "Sistem Informasi"
  },
  {
    "id": "abhiseka-susanto",
    "namaLengkap": "Abhiseka Susanto",
    "jurusan": "Ilmu Komputer"
  },
  {
    "id": "abraham-jordy-ollen",
    "namaLengkap": "Abraham Jordy Ollen",
    "jurusan": "Sistem Informasi"
  },
  {
    "id": "adam-caldipawell-sembiring",
    "namaLengkap": "Adam Caldipawell Sembiring ",
    "jurusan": "Ilmu Komputer"
  },
  {
    "id": "adelya-amanda",
    "namaLengkap": "Adelya Amanda",
    "jurusan": "Sistem Informasi"
  },
  {
    "id": "adiena-nimeesha-adiwinastwan",
    "namaLengkap": "Adiena Nimeesha Adiwinastwan",
    "jurusan": "Ilmu Komputer KKI"
  },
  {
    "id": "adinda-maharani-wardhana",
    "namaLengkap": "Adinda Maharani Wardhana",
    "jurusan": "Sistem Informasi"
  },
  {
    "id": "adinda-rosy-djalins",
    "namaLengkap": "Adinda Rosy Djalins",
    "jurusan": "Ilmu Komputer"
  },
  {
    "id": "aditya-dharma",
    "namaLengkap": "Aditya Dharma",
    "jurusan": "Sistem Informasi"
  },
  {
    "id": "adyo-arkan-prawira",
    "namaLengkap": "Adyo Arkan Prawira",
    "jurusan": "Ilmu Komputer"
  },
  {
    "id": "affandi-shafwan-soleh",
    "namaLengkap": "Affandi Shafwan Soleh",
    "jurusan": "Ilmu Komputer"
  },
  {
    "id": "agus-tini-sridewi",
    "namaLengkap": "Agus Tini Sridewi",
    "jurusan": "Ilmu Komputer"
  },
  {
    "id": "ahmad-aqeel-saniy",
    "namaLengkap": "Ahmad Aqeel Saniy",
    "jurusan": "Ilmu Komputer"
  },
  {
    "id": "ahmad-dzulfikar-as-shavy",
    "namaLengkap": "Ahmad Dzulfikar As Shavy",
    "jurusan": "Ilmu Komputer"
  },
  {
    "id": "ahmad-nizar-sauki",
    "namaLengkap": "Ahmad Nizar Sauki",
    "jurusan": "Ilmu Komputer"
  },
  {
    "id": "ahmad-nizar-sauki",
    "namaLengkap": "Ahmad Nizar Sauki",
    "jurusan": "Ilmu Komputer"
  },
  {
    "id": "aileen-josephine-halim",
    "namaLengkap": "Aileen Josephine Halim",
    "jurusan": "Sistem Informasi"
  },
  {
    "id": "aimee-ernanto",
    "namaLengkap": "Aimee Ernanto ",
    "jurusan": "Sistem Informasi"
  },
  {
    "id": "aisyah-hastomo",
    "namaLengkap": "Aisyah Hastomo",
    "jurusan": "Ilmu Komputer"
  },
  {
    "id": "akhdan-taufiq-syofyan",
    "namaLengkap": "Akhdan Taufiq Syofyan",
    "jurusan": "Ilmu Komputer"
  },
  {
    "id": "akhyar-rasyid-asy-syifa",
    "namaLengkap": "Akhyar Rasyid Asy syifa ",
    "jurusan": "Ilmu Komputer"
  },
  {
    "id": "akmal-nabil-fikri",
    "namaLengkap": "Akmal Nabil Fikri",
    "jurusan": "Ilmu Komputer"
  },
  {
    "id": "alano-davin-mandagi-awuy",
    "namaLengkap": "Alano Davin Mandagi Awuy",
    "jurusan": "Ilmu Komputer KKI"
  },
  {
    "id": "alexander-william-lim",
    "namaLengkap": "Alexander William Lim",
    "jurusan": "Ilmu Komputer"
  },
  {
    "id": "alfian-bassam-firjatullah",
    "namaLengkap": "Alfian Bassam Firjatullah",
    "jurusan": "Sistem Informasi"
  },
  {
    "id": "alica-kinar-deska",
    "namaLengkap": "Alica Kinar Deska ",
    "jurusan": "Sistem Informasi"
  },
  {
    "id": "aliefa-alsyafiandra-setiawati-mahdi",
    "namaLengkap": "Aliefa Alsyafiandra Setiawati Mahdi",
    "jurusan": "Ilmu Komputer"
  },
  {
    "id": "alisha-aline-athiyyah",
    "namaLengkap": "Alisha Aline Athiyyah",
    "jurusan": "Sistem Informasi"
  },
  {
    "id": "aliya-zahira-nadra",
    "namaLengkap": "Aliya Zahira Nadra",
    "jurusan": "Sistem Informasi"
  },
  {
    "id": "allan-kwek",
    "namaLengkap": "Allan Kwek",
    "jurusan": "Ilmu Komputer"
  },
  {
    "id": "alpha-sutha-media",
    "namaLengkap": "Alpha Sutha Media",
    "jurusan": "Ilmu Komputer"
  },
  {
    "id": "alwie-attar-elfandra",
    "namaLengkap": "Alwie Attar Elfandra",
    "jurusan": "Ilmu Komputer"
  },
  {
    "id": "alya-rasheeda-yuvana",
    "namaLengkap": "Alya Rasheeda Yuvana",
    "jurusan": "Sistem Informasi"
  },
  {
    "id": "alyssa-layla-sasti",
    "namaLengkap": "Alyssa Layla Sasti",
    "jurusan": "Ilmu Komputer"
  },
  {
    "id": "ameera-khaira-tawfiqa",
    "namaLengkap": "Ameera Khaira Tawfiqa",
    "jurusan": "Ilmu Komputer KKI"
  },
  {
    "id": "amirah-rizkita-setiadji",
    "namaLengkap": "Amirah Rizkita Setiadji",
    "jurusan": "Sistem Informasi"
  },
  {
    "id": "ammara-fasha-zia",
    "namaLengkap": "Ammara Fasha Zia",
    "jurusan": "Sistem Informasi"
  },
  {
    "id": "ananda-dwi-hanifa",
    "namaLengkap": "Ananda Dwi Hanifa",
    "jurusan": "Sistem Informasi"
  },
  {
    "id": "anders-willard-leo",
    "namaLengkap": "Anders Willard Leo",
    "jurusan": "Ilmu Komputer"
  },
  {
    "id": "andharu-hanif-achmadsyah",
    "namaLengkap": "Andharu Hanif Achmadsyah",
    "jurusan": "Sistem Informasi"
  },
  {
    "id": "andhika-nayaka-arya-wibowo",
    "namaLengkap": "Andhika Nayaka Arya Wibowo",
    "jurusan": "Ilmu Komputer KKI"
  },
  {
    "id": "andi-aqsa-mappatunru-marzuki",
    "namaLengkap": "Andi Aqsa Mappatunru Marzuki",
    "jurusan": "Ilmu Komputer"
  },
  {
    "id": "andi-muhammad-adlyn-fakhreyza-khairi-putra",
    "namaLengkap": "Andi Muhammad Adlyn Fakhreyza Khairi Putra",
    "jurusan": "Ilmu Komputer"
  },
  {
    "id": "andreas-timothy",
    "namaLengkap": "Andreas Timothy",
    "jurusan": "Ilmu Komputer"
  },
  {
    "id": "andrew-devito-aryo",
    "namaLengkap": "Andrew Devito Aryo",
    "jurusan": "Ilmu Komputer"
  },
  {
    "id": "andriyo-averill-fahrezi",
    "namaLengkap": "Andriyo Averill Fahrezi ",
    "jurusan": "Ilmu Komputer KKI"
  },
  {
    "id": "anggun-sasmitha-dewi",
    "namaLengkap": "Anggun Sasmitha Dewi",
    "jurusan": "Sistem Informasi"
  },
  {
    "id": "anindiyo-banu-prabasworo",
    "namaLengkap": "Anindiyo Banu Prabasworo",
    "jurusan": "Ilmu Komputer KKI"
  },
  {
    "id": "anindya-nabila-syifa",
    "namaLengkap": "Anindya Nabila Syifa",
    "jurusan": "Sistem Informasi"
  },
  {
    "id": "anita-khoirun-nisa",
    "namaLengkap": "Anita Khoirun Nisa'",
    "jurusan": "Ilmu Komputer"
  },
  {
    "id": "annisa-dwiyanti-ismael",
    "namaLengkap": "Annisa Dwiyanti Ismael",
    "jurusan": "Sistem Informasi"
  },
  {
    "id": "anthony-edbert-feriyanto",
    "namaLengkap": "Anthony Edbert Feriyanto",
    "jurusan": "Sistem Informasi"
  },
  {
    "id": "ardi-syahputra-amin",
    "namaLengkap": "Ardi Syahputra Amin",
    "jurusan": "Sistem Informasi"
  },
  {
    "id": "argya-farel-kasyara",
    "namaLengkap": "Argya Farel Kasyara",
    "jurusan": "Ilmu Komputer"
  },
  {
    "id": "arief-ridzki-darmawan",
    "namaLengkap": "Arief Ridzki Darmawan",
    "jurusan": "Ilmu Komputer"
  },
  {
    "id": "ariq-maulana-malik-ibrahim",
    "namaLengkap": "Ariq Maulana Malik Ibrahim",
    "jurusan": "Ilmu Komputer"
  },
  {
    "id": "arisha-shaista-aurelya",
    "namaLengkap": "Arisha Shaista Aurelya",
    "jurusan": "Ilmu Komputer"
  },
  {
    "id": "arya-gilang-prasetya",
    "namaLengkap": "Arya Gilang Prasetya",
    "jurusan": "Sistem Informasi"
  },
  {
    "id": "arya-raditya-kusuma",
    "namaLengkap": "Arya Raditya Kusuma",
    "jurusan": "Ilmu Komputer"
  },
  {
    "id": "arzaka-raffan-mawardi",
    "namaLengkap": "Arzaka Raffan Mawardi",
    "jurusan": "Ilmu Komputer"
  },
  {
    "id": "asyer-samuel-marpaung",
    "namaLengkap": "Asyer Samuel Marpaung ",
    "jurusan": "Sistem Informasi"
  },
  {
    "id": "athaillah-sifa-tanudatar",
    "namaLengkap": "Athaillah Sifa Tanudatar",
    "jurusan": "Sistem Informasi"
  },
  {
    "id": "athallah-damar-jiwanto",
    "namaLengkap": "Athallah Damar Jiwanto",
    "jurusan": "Ilmu Komputer"
  },
  {
    "id": "athallah-nadhif",
    "namaLengkap": "Athallah Nadhif",
    "jurusan": "Sistem Informasi"
  },
  {
    "id": "athallah-wibowo",
    "namaLengkap": "Athallah Wibowo",
    "jurusan": "Sistem Informasi"
  },
  {
    "id": "athazahra-nabila-ruby",
    "namaLengkap": "Athazahra Nabila Ruby",
    "jurusan": "Ilmu Komputer KKI"
  },
  {
    "id": "awalinda-dimmi",
    "namaLengkap": "Awalinda Dimmi ",
    "jurusan": "Ilmu Komputer"
  },
  {
    "id": "azzahra-salsabila",
    "namaLengkap": "Azzahra Salsabila",
    "jurusan": "Sistem Informasi"
  },
  {
    "id": "bastian-adiputra-siregar",
    "namaLengkap": "Bastian Adiputra Siregar ",
    "jurusan": "Ilmu Komputer"
  },
  {
    "id": "belva-ghani-abhinaya",
    "namaLengkap": "Belva Ghani Abhinaya ",
    "jurusan": "Ilmu Komputer"
  },
  {
    "id": "bertrand-gwynfory-iskandar",
    "namaLengkap": "Bertrand Gwynfory Iskandar",
    "jurusan": "Ilmu Komputer"
  },
  {
    "id": "brenda-po-lok-fahida",
    "namaLengkap": "Brenda Po Lok Fahida",
    "jurusan": "Ilmu Komputer"
  },
  {
    "id": "brian-altan",
    "namaLengkap": "Brian Altan",
    "jurusan": "Ilmu Komputer"
  },
  {
    "id": "bryan-mitch",
    "namaLengkap": "Bryan Mitch",
    "jurusan": "Sistem Informasi"
  },
  {
    "id": "bryant-warrick-cai",
    "namaLengkap": "Bryant Warrick Cai",
    "jurusan": "Ilmu Komputer KKI"
  },
  {
    "id": "cahya-bagus-gautama-gozales",
    "namaLengkap": "Cahya Bagus Gautama Gozales",
    "jurusan": "Sistem Informasi"
  },
  {
    "id": "calvin-joy-tarigan",
    "namaLengkap": "Calvin Joy Tarigan",
    "jurusan": "Ilmu Komputer"
  },
  {
    "id": "carleano-ravelza-wongso",
    "namaLengkap": "Carleano Ravelza Wongso",
    "jurusan": "Ilmu Komputer"
  },
  {
    "id": "catherine-aurellia",
    "namaLengkap": "Catherine Aurellia",
    "jurusan": "Ilmu Komputer KKI"
  },
  {
    "id": "chiara-aqmarina-diankusumo",
    "namaLengkap": "Chiara Aqmarina Diankusumo",
    "jurusan": "Ilmu Komputer KKI"
  },
  {
    "id": "christ-jonathan",
    "namaLengkap": "Christ Jonathan",
    "jurusan": "Sistem Informasi"
  },
  {
    "id": "christian-raphael-heryanto",
    "namaLengkap": "Christian Raphael Heryanto",
    "jurusan": "Ilmu Komputer"
  },
  {
    "id": "christian-yudistira-hermawan",
    "namaLengkap": "Christian Yudistira Hermawan",
    "jurusan": "Ilmu Komputer"
  },
  {
    "id": "christopher-matthew-hendarson",
    "namaLengkap": "Christopher Matthew Hendarson",
    "jurusan": "Sistem Informasi"
  },
  {
    "id": "cindy-octavia",
    "namaLengkap": "Cindy Octavia ",
    "jurusan": "Sistem Informasi"
  },
  {
    "id": "clara-aurelia-setiady",
    "namaLengkap": "Clara Aurelia Setiady",
    "jurusan": "Sistem Informasi"
  },
  {
    "id": "clarissa-i-p",
    "namaLengkap": "Clarissa I. P.",
    "jurusan": "Sistem Informasi"
  },
  {
    "id": "claudia-paskalia-koesno",
    "namaLengkap": "Claudia Paskalia Koesno",
    "jurusan": "Sistem Informasi"
  },
  {
    "id": "cleo-excellen-iskandar",
    "namaLengkap": "Cleo Excellen Iskandar",
    "jurusan": "Ilmu Komputer"
  },
  {
    "id": "crysandya-vic-rajendra",
    "namaLengkap": "Crysandya Vic Rajendra",
    "jurusan": "Sistem Informasi"
  },
  {
    "id": "daanish-inayat-rahman",
    "namaLengkap": "Daanish Inayat Rahman",
    "jurusan": "Sistem Informasi"
  },
  {
    "id": "daffa-abhipraya-putra",
    "namaLengkap": "Daffa Abhipraya Putra",
    "jurusan": "Ilmu Komputer"
  },
  {
    "id": "daffa-aqil-mahmud",
    "namaLengkap": "Daffa Aqil Mahmud",
    "jurusan": "Ilmu Komputer"
  },
  {
    "id": "daffa-desra-hastiar",
    "namaLengkap": "Daffa Desra Hastiar",
    "jurusan": "Sistem Informasi"
  },
  {
    "id": "daffa-naufal-rahadian",
    "namaLengkap": "Daffa Naufal Rahadian",
    "jurusan": "Ilmu Komputer"
  },
  {
    "id": "daffa-rayhan-ananda",
    "namaLengkap": "Daffa Rayhan Ananda",
    "jurusan": "Ilmu Komputer"
  },
  {
    "id": "damar-aryaputra-rahman",
    "namaLengkap": "Damar Aryaputra Rahman",
    "jurusan": "Ilmu Komputer KKI"
  },
  {
    "id": "dandi-apriyansyah",
    "namaLengkap": "Dandi Apriyansyah ",
    "jurusan": "Sistem Informasi"
  },
  {
    "id": "daniel-angger-dewandaru",
    "namaLengkap": "Daniel Angger Dewandaru",
    "jurusan": "Ilmu Komputer"
  },
  {
    "id": "daniel-ferdiansyah",
    "namaLengkap": "Daniel Ferdiansyah",
    "jurusan": "Ilmu Komputer"
  },
  {
    "id": "daniel-liman",
    "namaLengkap": "Daniel Liman",
    "jurusan": "Ilmu Komputer"
  },
  {
    "id": "danniel",
    "namaLengkap": "Danniel",
    "jurusan": "Ilmu Komputer"
  },
  {
    "id": "dara-zakya-apriani",
    "namaLengkap": "Dara Zakya Apriani",
    "jurusan": "Sistem Informasi"
  },
  {
    "id": "darren-aldrich",
    "namaLengkap": "Darren Aldrich",
    "jurusan": "Ilmu Komputer"
  },
  {
    "id": "darren-marcello-sidabutar",
    "namaLengkap": "Darren Marcello Sidabutar",
    "jurusan": "Ilmu Komputer KKI"
  },
  {
    "id": "dava-hannas-putra",
    "namaLengkap": "Dava Hannas Putra",
    "jurusan": "Sistem Informasi"
  },
  {
    "id": "david-juan-ananda",
    "namaLengkap": "David Juan Ananda",
    "jurusan": "Sistem Informasi"
  },
  {
    "id": "deanita-sekar-kinasih",
    "namaLengkap": "Deanita Sekar Kinasih",
    "jurusan": "Ilmu Komputer"
  },
  {
    "id": "delya-ardiyanti",
    "namaLengkap": "Delya Ardiyanti",
    "jurusan": "Sistem Informasi"
  },
  {
    "id": "derensh-pandian",
    "namaLengkap": "Derensh Pandian",
    "jurusan": "Ilmu Komputer KKI"
  },
  {
    "id": "dhafin-putra-nugraha",
    "namaLengkap": "Dhafin Putra Nugraha",
    "jurusan": "Sistem Informasi"
  },
  {
    "id": "dhania-tiaraputri-herdiani",
    "namaLengkap": "Dhania Tiaraputri Herdiani",
    "jurusan": "Sistem Informasi"
  },
  {
    "id": "dicky-bayu-sadewo",
    "namaLengkap": "Dicky Bayu Sadewo",
    "jurusan": "Ilmu Komputer"
  },
  {
    "id": "dinda-dinanti",
    "namaLengkap": "Dinda Dinanti",
    "jurusan": "Sistem Informasi"
  },
  {
    "id": "dionysius-davis",
    "namaLengkap": "Dionysius Davis",
    "jurusan": "Ilmu Komputer"
  },
  {
    "id": "dzaki-abrar-fatihul-ihsan",
    "namaLengkap": "Dzaki Abrar Fatihul Ihsan",
    "jurusan": "Sistem Informasi"
  },
  {
    "id": "edmond-christian",
    "namaLengkap": "Edmond Christian",
    "jurusan": "Ilmu Komputer"
  },
  {
    "id": "emanuella-abygail-rotua-siahaan",
    "namaLengkap": "Emanuella Abygail Rotua Siahaan",
    "jurusan": "Ilmu Komputer"
  },
  {
    "id": "erdafa-andikri",
    "namaLengkap": "Erdafa Andikri",
    "jurusan": "Ilmu Komputer"
  },
  {
    "id": "erland-hafizh-aristovi",
    "namaLengkap": "Erland Hafizh Aristovi",
    "jurusan": "Sistem Informasi"
  },
  {
    "id": "eva-yunia-aliyanshah",
    "namaLengkap": "Eva Yunia Aliyanshah",
    "jurusan": "Sistem Informasi"
  },
  {
    "id": "evelyn-depthios",
    "namaLengkap": "Evelyn Depthios",
    "jurusan": "Sistem Informasi"
  },
  {
    "id": "ezar-akhdan-shada-surahman",
    "namaLengkap": "Ezar Akhdan Shada Surahman",
    "jurusan": "Sistem Informasi"
  },
  {
    "id": "fadhli-raihan-ardiansyah",
    "namaLengkap": "Fadhli Raihan Ardiansyah",
    "jurusan": "Ilmu Komputer"
  },
  {
    "id": "fadhlurohman-dzaki",
    "namaLengkap": "Fadhlurohman Dzaki",
    "jurusan": "Ilmu Komputer"
  },
  {
    "id": "fadiansah-feryan-fatha",
    "namaLengkap": "Fadiansah Feryan Fatha",
    "jurusan": "Sistem Informasi"
  },
  {
    "id": "faiz-akram-pribadi",
    "namaLengkap": "Faiz Akram Pribadi",
    "jurusan": "Sistem Informasi"
  },
  {
    "id": "faiz-assabil-firdaus",
    "namaLengkap": "Faiz Assabil Firdaus ",
    "jurusan": "Ilmu Komputer"
  },
  {
    "id": "fakhri-habibi",
    "namaLengkap": "Fakhri Habibi",
    "jurusan": "Sistem Informasi"
  },
  {
    "id": "fakhri-reza-abinaya",
    "namaLengkap": "Fakhri Reza Abinaya",
    "jurusan": "Ilmu Komputer"
  },
  {
    "id": "fakhriyah-ghania-putri",
    "namaLengkap": "Fakhriyah Ghania Putri",
    "jurusan": "Sistem Informasi"
  },
  {
    "id": "farhan-adelio-prayata",
    "namaLengkap": "Farhan Adelio Prayata",
    "jurusan": "Sistem Informasi"
  },
  {
    "id": "farhan-dwi-putra",
    "namaLengkap": "Farhan Dwi Putra",
    "jurusan": "Sistem Informasi"
  },
  {
    "id": "fariz-muhammad-rayhansyah-ramadhan",
    "namaLengkap": "Fariz Muhammad Rayhansyah Ramadhan",
    "jurusan": "Sistem Informasi"
  },
  {
    "id": "farrel-ahmad-ilyasa",
    "namaLengkap": "Farrel Ahmad Ilyasa",
    "jurusan": "Ilmu Komputer"
  },
  {
    "id": "farrel-athalla-muljawan",
    "namaLengkap": "Farrel Athalla Muljawan",
    "jurusan": "Ilmu Komputer"
  },
  {
    "id": "farrel-dharmawan-dwiyudanto",
    "namaLengkap": "Farrel Dharmawan Dwiyudanto",
    "jurusan": "Sistem Informasi"
  },
  {
    "id": "farrel-reksa-prawira",
    "namaLengkap": "Farrel Reksa Prawira",
    "jurusan": "Sistem Informasi"
  },
  {
    "id": "farrell-zidane-raihandrawan",
    "namaLengkap": "Farrell Zidane Raihandrawan",
    "jurusan": "Sistem Informasi"
  },
  {
    "id": "fathurrahman-kesuma-ridwan",
    "namaLengkap": "Fathurrahman Kesuma Ridwan",
    "jurusan": "Ilmu Komputer"
  },
  {
    "id": "fauzan-putra-sanjaya",
    "namaLengkap": "Fauzan Putra Sanjaya",
    "jurusan": "Sistem Informasi"
  },
  {
    "id": "favian-zhafif-rizqullah-permana",
    "namaLengkap": "Favian Zhafif Rizqullah Permana",
    "jurusan": "Ilmu Komputer"
  },
  {
    "id": "febrian-arifianto-widyadhana",
    "namaLengkap": "Febrian Arifianto Widyadhana",
    "jurusan": "Sistem Informasi"
  },
  {
    "id": "felita-zahra-d",
    "namaLengkap": "Felita Zahra D",
    "jurusan": "Sistem Informasi"
  },
  {
    "id": "ferdinand-bonfilio-simamora",
    "namaLengkap": "Ferdinand Bonfilio Simamora",
    "jurusan": "Ilmu Komputer KKI"
  },
  {
    "id": "figo-favian-ragazo",
    "namaLengkap": "Figo Favian Ragazo",
    "jurusan": "Ilmu Komputer"
  },
  {
    "id": "fikar-hilmi-adhrevi",
    "namaLengkap": "Fikar Hilmi Adhrevi",
    "jurusan": "Sistem Informasi"
  },
  {
    "id": "filbert-aurelian-tjiaranata",
    "namaLengkap": "Filbert Aurelian Tjiaranata",
    "jurusan": "Ilmu Komputer"
  },
  {
    "id": "flori-andrea-ng",
    "namaLengkap": "Flori Andrea Ng",
    "jurusan": "Ilmu Komputer KKI"
  },
  {
    "id": "franky-raymarcell-sinaga",
    "namaLengkap": "Franky Raymarcell Sinaga",
    "jurusan": "Ilmu Komputer"
  },
  {
    "id": "fransisca-ellya-bunaren",
    "namaLengkap": "Fransisca Ellya Bunaren",
    "jurusan": "Ilmu Komputer"
  },
  {
    "id": "freia-arianti-zulaika",
    "namaLengkap": "Freia Arianti Zulaika",
    "jurusan": "Ilmu Komputer"
  },
  {
    "id": "gabriel-selwas-aboyaman-fenanlampir",
    "namaLengkap": "Gabriel Selwas Aboyaman Fenanlampir ",
    "jurusan": "Ilmu Komputer"
  },
  {
    "id": "geordie-vannese-hardjanto",
    "namaLengkap": "Geordie Vannese Hardjanto",
    "jurusan": "Ilmu Komputer"
  },
  {
    "id": "ghiranza-athaya-hamid",
    "namaLengkap": "Ghiranza Athaya Hamid",
    "jurusan": "Sistem Informasi"
  },
  {
    "id": "gilbert-kristian",
    "namaLengkap": "Gilbert Kristian",
    "jurusan": "Ilmu Komputer"
  },
  {
    "id": "gnade-yuka",
    "namaLengkap": "Gnade Yuka",
    "jurusan": "Sistem Informasi"
  },
  {
    "id": "grace-karina",
    "namaLengkap": "Grace Karina",
    "jurusan": "Ilmu Komputer"
  },
  {
    "id": "habib-ash-shiddiq",
    "namaLengkap": "Habib Ash Shiddiq",
    "jurusan": "Sistem Informasi"
  },
  {
    "id": "hadyan-fachri",
    "namaLengkap": "Hadyan Fachri",
    "jurusan": "Ilmu Komputer"
  },
  {
    "id": "hafidz-aliraqi",
    "namaLengkap": "Hafidz Aliraqi",
    "jurusan": "Ilmu Komputer"
  },
  {
    "id": "hafizh-surya-mustafa-zen",
    "namaLengkap": "Hafizh Surya Mustafa Zen",
    "jurusan": "Ilmu Komputer KKI"
  },
  {
    "id": "haliza-nafiah-syakira-arfa",
    "namaLengkap": "Haliza Nafiah Syakira Arfa",
    "jurusan": "Ilmu Komputer"
  },
  {
    "id": "harman-hakim",
    "namaLengkap": "Harman Hakim",
    "jurusan": "Sistem Informasi"
  },
  {
    "id": "heinrich-edric-damadika-suselo",
    "namaLengkap": "Heinrich Edric Damadika Suselo ",
    "jurusan": "Ilmu Komputer KKI"
  },
  {
    "id": "henry-aditya-kosasi",
    "namaLengkap": "Henry Aditya Kosasi",
    "jurusan": "Ilmu Komputer"
  },
  {
    "id": "hizounya-maycinto-alkian",
    "namaLengkap": "Hizounya Maycinto Alkian",
    "jurusan": "Sistem Informasi"
  },
  {
    "id": "hubban-syadid",
    "namaLengkap": "Hubban Syadid",
    "jurusan": "Sistem Informasi"
  },
  {
    "id": "husin-hidayatul-hakim",
    "namaLengkap": "Husin Hidayatul Hakim",
    "jurusan": "Ilmu Komputer"
  },
  {
    "id": "ida-made-revindra-dikta-mahendra",
    "namaLengkap": "Ida Made Revindra Dikta Mahendra",
    "jurusan": "Ilmu Komputer"
  },
  {
    "id": "ignasius-bramantya-widiprasetya",
    "namaLengkap": "Ignasius Bramantya Widiprasetya ",
    "jurusan": "Sistem Informasi"
  },
  {
    "id": "ihsan-panji-rahmawan",
    "namaLengkap": "Ihsan Panji Rahmawan",
    "jurusan": "Ilmu Komputer"
  },
  {
    "id": "ilham-ghani-adrin-sapta",
    "namaLengkap": "Ilham Ghani Adrin Sapta",
    "jurusan": "Sistem Informasi"
  },
  {
    "id": "ilham-satya-nusabhakti",
    "namaLengkap": "Ilham Satya Nusabhakti",
    "jurusan": "Ilmu Komputer"
  },
  {
    "id": "imam-fajri",
    "namaLengkap": "Imam Fajri",
    "jurusan": "Sistem Informasi"
  },
  {
    "id": "imroatul-hamidah",
    "namaLengkap": "Imroatul Hamidah ",
    "jurusan": "Sistem Informasi"
  },
  {
    "id": "indah-cahya-puspitahati",
    "namaLengkap": "Indah Cahya Puspitahati",
    "jurusan": "Sistem Informasi"
  },
  {
    "id": "irfan-rizqi-nurrahman",
    "namaLengkap": "Irfan Rizqi Nurrahman",
    "jurusan": "Ilmu Komputer"
  },
  {
    "id": "irma-nia-alwijah",
    "namaLengkap": "Irma Nia Alwijah",
    "jurusan": "Sistem Informasi"
  },
  {
    "id": "isaac-jesse-boentoro",
    "namaLengkap": "Isaac Jesse Boentoro",
    "jurusan": "Ilmu Komputer KKI"
  },
  {
    "id": "ischika-afrilla",
    "namaLengkap": "Ischika Afrilla",
    "jurusan": "Ilmu Komputer"
  },
  {
    "id": "ischika-afrilla",
    "namaLengkap": "Ischika Afrilla",
    "jurusan": "Ilmu Komputer"
  },
  {
    "id": "ismail-yanuar-anwas",
    "namaLengkap": "Ismail Yanuar Anwas",
    "jurusan": "Sistem Informasi"
  },
  {
    "id": "ivan-jehuda-angi",
    "namaLengkap": "Ivan Jehuda Angi",
    "jurusan": "Ilmu Komputer"
  },
  {
    "id": "janssen-benedict",
    "namaLengkap": "Janssen Benedict",
    "jurusan": "Ilmu Komputer"
  },
  {
    "id": "jasmine-rakhaila-wibisono",
    "namaLengkap": "Jasmine Rakhaila Wibisono",
    "jurusan": "Sistem Informasi"
  },
  {
    "id": "jeremi-felix-adiyatma",
    "namaLengkap": "Jeremi Felix Adiyatma",
    "jurusan": "Sistem Informasi"
  },
  {
    "id": "jeremia-rangga-setyawan",
    "namaLengkap": "Jeremia Rangga Setyawan",
    "jurusan": "Sistem Informasi"
  },
  {
    "id": "joanne-kenisa-adelina-limena",
    "namaLengkap": "Joanne Kenisa Adelina Limena",
    "jurusan": "Sistem Informasi"
  },
  {
    "id": "joe-mathew-rusli",
    "namaLengkap": "Joe Mathew Rusli",
    "jurusan": "Ilmu Komputer"
  },
  {
    "id": "joel-anand-garcia-sinaga",
    "namaLengkap": "Joel Anand Garcia Sinaga",
    "jurusan": "Ilmu Komputer"
  },
  {
    "id": "joshua-elisha-shalom-soedarmintarto",
    "namaLengkap": "Joshua Elisha Shalom Soedarmintarto",
    "jurusan": "Ilmu Komputer"
  },
  {
    "id": "joshua-hans-vito-soehendra",
    "namaLengkap": "Joshua Hans Vito Soehendra ",
    "jurusan": "Sistem Informasi"
  },
  {
    "id": "joshua-montolalu",
    "namaLengkap": "Joshua Montolalu",
    "jurusan": "Ilmu Komputer"
  },
  {
    "id": "juan-lukius-barnaby",
    "namaLengkap": "Juan Lukius Barnaby",
    "jurusan": "Sistem Informasi"
  },
  {
    "id": "kadek-savitri",
    "namaLengkap": "Kadek Savitri",
    "jurusan": "Sistem Informasi"
  },
  {
    "id": "kaindra-rizq-sachio",
    "namaLengkap": "Kaindra Rizq Sachio",
    "jurusan": "Ilmu Komputer"
  },
  {
    "id": "kania-almyra-bilqist",
    "namaLengkap": "Kania Almyra Bilqist",
    "jurusan": "Sistem Informasi"
  },
  {
    "id": "karina-maharani",
    "namaLengkap": "Karina Maharani ",
    "jurusan": "Sistem Informasi"
  },
  {
    "id": "karolina-jocelyn",
    "namaLengkap": "Karolina Jocelyn",
    "jurusan": "Ilmu Komputer"
  },
  {
    "id": "kayla-agrata-budiawan",
    "namaLengkap": "Kayla Agrata Budiawan",
    "jurusan": "Sistem Informasi"
  },
  {
    "id": "kayla-soraya-djakaria",
    "namaLengkap": "Kayla Soraya Djakaria",
    "jurusan": "Ilmu Komputer KKI"
  },
  {
    "id": "keira-diaz-nabhani",
    "namaLengkap": "Keira Diaz Nabhani",
    "jurusan": "Ilmu Komputer KKI"
  },
  {
    "id": "kevin-adriano",
    "namaLengkap": "Kevin Adriano",
    "jurusan": "Ilmu Komputer KKI"
  },
  {
    "id": "kezia-salsalina-agtyra-sebayang",
    "namaLengkap": "Kezia Salsalina Agtyra Sebayang",
    "jurusan": "Ilmu Komputer KKI"
  },
  {
    "id": "khairul-bintang",
    "namaLengkap": "Khairul Bintang",
    "jurusan": "Sistem Informasi"
  },
  {
    "id": "khansa-khairunisa",
    "namaLengkap": "Khansa Khairunisa ",
    "jurusan": "Ilmu Komputer"
  },
  {
    "id": "khayla-naura-ulya-luqyana",
    "namaLengkap": "Khayla Naura Ulya Luqyana ",
    "jurusan": "Sistem Informasi"
  },
  {
    "id": "khoirul-azmi",
    "namaLengkap": "Khoirul Azmi",
    "jurusan": "Sistem Informasi"
  },
  {
    "id": "krisna-putra-purnomo",
    "namaLengkap": "Krisna Putra Purnomo",
    "jurusan": "Ilmu Komputer"
  },
  {
    "id": "kukuh-cikal-yuntama",
    "namaLengkap": "Kukuh Cikal Yuntama",
    "jurusan": "Sistem Informasi"
  },
  {
    "id": "kusuma-ratih-hanindyani",
    "namaLengkap": "Kusuma Ratih Hanindyani",
    "jurusan": "Ilmu Komputer KKI"
  },
  {
    "id": "laurentius-arlana-farel-mahardika",
    "namaLengkap": "Laurentius Arlana Farel Mahardika ",
    "jurusan": "Ilmu Komputer"
  },
  {
    "id": "leonita-cecilia",
    "namaLengkap": "Leonita Cecilia",
    "jurusan": "Sistem Informasi"
  },
  {
    "id": "lisa-margaretha-esron-tobing",
    "namaLengkap": "Lisa Margaretha Esron Tobing",
    "jurusan": "Sistem Informasi"
  },
  {
    "id": "luqmanul-hakim",
    "namaLengkap": "Luqmanul Hakim",
    "jurusan": "Ilmu Komputer"
  },
  {
    "id": "luvenia-feodora-saragih",
    "namaLengkap": "Luvenia Feodora Saragih",
    "jurusan": "Sistem Informasi"
  },
  {
    "id": "m-alvin-rheinaldy-gz",
    "namaLengkap": "M. Alvin Rheinaldy G.Z.",
    "jurusan": "Ilmu Komputer"
  },
  {
    "id": "m-arvin-wijayanto",
    "namaLengkap": "M. Arvin Wijayanto",
    "jurusan": "Sistem Informasi"
  },
  {
    "id": "muhammad-rafli-esa-pradana",
    "namaLengkap": "MUHAMMAD RAFLI ESA PRADANA ",
    "jurusan": "Ilmu Komputer"
  },
  {
    "id": "made-izzy-prema-dharma",
    "namaLengkap": "Made Izzy Prema Dharma",
    "jurusan": "Ilmu Komputer KKI"
  },
  {
    "id": "madeline-clairine-gultom",
    "namaLengkap": "Madeline Clairine Gultom ",
    "jurusan": "Ilmu Komputer"
  },
  {
    "id": "mahanangkwa-kawisigdayan-sukmana",
    "namaLengkap": "Mahanangkwa Kawisigdayan Sukmana ",
    "jurusan": "Sistem Informasi"
  },
  {
    "id": "maibyna-khairanisya",
    "namaLengkap": "Maibyna Khairanisya",
    "jurusan": "Sistem Informasi"
  },
  {
    "id": "maira-shasmeen-mazaya",
    "namaLengkap": "Maira Shasmeen Mazaya",
    "jurusan": "Sistem Informasi"
  },
  {
    "id": "maira-shasmeen-mazaya",
    "namaLengkap": "Maira Shasmeen Mazaya",
    "jurusan": "Sistem Informasi"
  },
  {
    "id": "malika-atha-indurasmi",
    "namaLengkap": "Malika Atha Indurasmi",
    "jurusan": "Sistem Informasi"
  },
  {
    "id": "malvin-muhammad-raqin",
    "namaLengkap": "Malvin Muhammad Raqin",
    "jurusan": "Ilmu Komputer"
  },
  {
    "id": "malvin-scafi",
    "namaLengkap": "Malvin Scafi",
    "jurusan": "Ilmu Komputer"
  },
  {
    "id": "marla-marlena",
    "namaLengkap": "Marla Marlena",
    "jurusan": "Sistem Informasi"
  },
  {
    "id": "mawla-raditya-pambudi",
    "namaLengkap": "Mawla Raditya Pambudi",
    "jurusan": "Sistem Informasi"
  },
  {
    "id": "meisya-najla-aqilah",
    "namaLengkap": "Meisya Najla Aqilah",
    "jurusan": "Sistem Informasi"
  },
  {
    "id": "meutia-fajriyah",
    "namaLengkap": "Meutia Fajriyah",
    "jurusan": "Sistem Informasi"
  },
  {
    "id": "michael-ignasius",
    "namaLengkap": "Michael Ignasius",
    "jurusan": "Ilmu Komputer"
  },
  {
    "id": "micheline-wijaya-limbergh",
    "namaLengkap": "Micheline Wijaya Limbergh",
    "jurusan": "Ilmu Komputer"
  },
  {
    "id": "min-kim",
    "namaLengkap": "Min Kim",
    "jurusan": "Ilmu Komputer KKI"
  },
  {
    "id": "mirfak-naufal-pratama-putra",
    "namaLengkap": "Mirfak Naufal Pratama Putra",
    "jurusan": "Ilmu Komputer"
  },
  {
    "id": "mirza-athallah-salman",
    "namaLengkap": "Mirza Athallah Salman",
    "jurusan": "Sistem Informasi"
  },
  {
    "id": "mohamad-rafli-hidayat",
    "namaLengkap": "Mohamad Rafli Hidayat",
    "jurusan": "Sistem Informasi"
  },
  {
    "id": "mohammad-raihan-razzani",
    "namaLengkap": "Mohammad Raihan Razzani",
    "jurusan": "Sistem Informasi"
  },
  {
    "id": "muh-syauqillah-pamiluddin",
    "namaLengkap": "Muh. Syauqillah Pamiluddin",
    "jurusan": "Sistem Informasi"
  },
  {
    "id": "muhammad-abyasa-pratama",
    "namaLengkap": "Muhammad Abyasa Pratama",
    "jurusan": "Ilmu Komputer"
  },
  {
    "id": "muhammad-adiansyah",
    "namaLengkap": "Muhammad Adiansyah ",
    "jurusan": "Ilmu Komputer"
  },
  {
    "id": "muhammad-afwan-hafizh",
    "namaLengkap": "Muhammad Afwan Hafizh",
    "jurusan": "Ilmu Komputer"
  },
  {
    "id": "muhammad-akmal-abdul-halim",
    "namaLengkap": "Muhammad Akmal Abdul Halim ",
    "jurusan": "Ilmu Komputer"
  },
  {
    "id": "muhammad-albyarto-ghazali",
    "namaLengkap": "Muhammad Albyarto Ghazali ",
    "jurusan": "Ilmu Komputer"
  },
  {
    "id": "muhammad-almerazka-yocendra",
    "namaLengkap": "Muhammad Almerazka Yocendra",
    "jurusan": "Ilmu Komputer"
  },
  {
    "id": "muhammad-azzam",
    "namaLengkap": "Muhammad Azzam",
    "jurusan": "Sistem Informasi"
  },
  {
    "id": "muhammad-brian-subekti",
    "namaLengkap": "Muhammad Brian Subekti",
    "jurusan": "Ilmu Komputer KKI"
  },
  {
    "id": "muhammad-daffa-abyaz-tjiptadi",
    "namaLengkap": "Muhammad Daffa Abyaz Tjiptadi",
    "jurusan": "Sistem Informasi"
  },
  {
    "id": "muhammad-dzikri-ilmansyah",
    "namaLengkap": "Muhammad Dzikri Ilmansyah",
    "jurusan": "Sistem Informasi"
  },
  {
    "id": "muhammad-fadhil-nur-aziz",
    "namaLengkap": "Muhammad Fadhil Nur Aziz",
    "jurusan": "Sistem Informasi"
  },
  {
    "id": "muhammad-fadhlan-arradhi",
    "namaLengkap": "Muhammad Fadhlan Arradhi",
    "jurusan": "Sistem Informasi"
  },
  {
    "id": "muhammad-fadhlan-karimuddin",
    "namaLengkap": "Muhammad Fadhlan Karimuddin ",
    "jurusan": "Ilmu Komputer"
  },
  {
    "id": "muhammad-faizi-ismady-supardjo",
    "namaLengkap": "Muhammad Faizi Ismady Supardjo",
    "jurusan": "Ilmu Komputer"
  },
  {
    "id": "muhammad-fakhri",
    "namaLengkap": "Muhammad Fakhri",
    "jurusan": "Sistem Informasi"
  },
  {
    "id": "muhammad-falah-marzuq",
    "namaLengkap": "Muhammad Falah Marzuq ",
    "jurusan": "Sistem Informasi"
  },
  {
    "id": "muhammad-farhan-adya-hermawan",
    "namaLengkap": "Muhammad Farhan Adya Hermawan",
    "jurusan": "Sistem Informasi"
  },
  {
    "id": "muhammad-farhan-ramadhan",
    "namaLengkap": "Muhammad Farhan Ramadhan",
    "jurusan": "Sistem Informasi"
  },
  {
    "id": "muhammad-farid-hasabi",
    "namaLengkap": "Muhammad Farid Hasabi ",
    "jurusan": "Ilmu Komputer"
  },
  {
    "id": "muhammad-fawwaz-edsa-fatin-setiawan",
    "namaLengkap": "Muhammad Fawwaz Edsa Fatin Setiawan ",
    "jurusan": "Sistem Informasi"
  },
  {
    "id": "muhammad-fayyed-as-shidqi",
    "namaLengkap": "Muhammad Fayyed As Shidqi",
    "jurusan": "Ilmu Komputer"
  },
  {
    "id": "muhammad-fazil-tirtana",
    "namaLengkap": "Muhammad Fazil Tirtana",
    "jurusan": "Ilmu Komputer"
  },
  {
    "id": "muhammad-firaz-al-aqib",
    "namaLengkap": "Muhammad Firaz Al Aqib",
    "jurusan": "Ilmu Komputer"
  },
  {
    "id": "muhammad-ghathaf-fariz-abiyyu",
    "namaLengkap": "Muhammad Ghathaf Fariz Abiyyu",
    "jurusan": "Sistem Informasi"
  },
  {
    "id": "muhammad-ghaza-fadhlilbaqi",
    "namaLengkap": "Muhammad Ghaza Fadhlilbaqi",
    "jurusan": "Ilmu Komputer KKI"
  },
  {
    "id": "muhammad-hamid",
    "namaLengkap": "Muhammad Hamid",
    "jurusan": "Ilmu Komputer"
  },
  {
    "id": "muhammad-hibrizi-farghana",
    "namaLengkap": "Muhammad Hibrizi Farghana ",
    "jurusan": "Sistem Informasi"
  },
  {
    "id": "muhammad-jordan-ar-razi-aziz",
    "namaLengkap": "Muhammad Jordan Ar-Razi Aziz",
    "jurusan": "Ilmu Komputer KKI"
  },
  {
    "id": "muhammad-luthfi-febriyan",
    "namaLengkap": "Muhammad Luthfi Febriyan",
    "jurusan": "Sistem Informasi"
  },
  {
    "id": "muhammad-nadzim-tahara",
    "namaLengkap": "Muhammad Nadzim Tahara",
    "jurusan": "Sistem Informasi"
  },
  {
    "id": "muhammad-naufal-ramadhan",
    "namaLengkap": "Muhammad Naufal Ramadhan ",
    "jurusan": "Ilmu Komputer"
  },
  {
    "id": "muhammad-radhiya-arshq",
    "namaLengkap": "Muhammad Radhiya Arshq ",
    "jurusan": "Ilmu Komputer"
  },
  {
    "id": "muhammad-raditya-indrastata-norman",
    "namaLengkap": "Muhammad Raditya Indrastata Norman",
    "jurusan": "Ilmu Komputer KKI"
  },
  {
    "id": "muhammad-raihan-maulana",
    "namaLengkap": "Muhammad Raihan Maulana",
    "jurusan": "Ilmu Komputer"
  },
  {
    "id": "muhammad-rayyan-wiradana",
    "namaLengkap": "Muhammad Rayyan Wiradana",
    "jurusan": "Sistem Informasi"
  },
  {
    "id": "muhammad-reyhan-ardian",
    "namaLengkap": "Muhammad Reyhan Ardian",
    "jurusan": "Ilmu Komputer"
  },
  {
    "id": "muhammad-rizky-ramadhani",
    "namaLengkap": "Muhammad Rizky Ramadhani",
    "jurusan": "Sistem Informasi"
  },
  {
    "id": "muhammad-ruzbehan-baqli",
    "namaLengkap": "Muhammad Ruzbehan Baqli",
    "jurusan": "Ilmu Komputer"
  },
  {
    "id": "muhammad-satria-aleka-ramadhan",
    "namaLengkap": "Muhammad Satria Aleka Ramadhan",
    "jurusan": "Ilmu Komputer"
  },
  {
    "id": "muhammad-wendy-fyfo-anggara",
    "namaLengkap": "Muhammad Wendy Fyfo Anggara",
    "jurusan": "Ilmu Komputer"
  },
  {
    "id": "muhammad-yahya-ayyas",
    "namaLengkap": "Muhammad Yahya Ayyas",
    "jurusan": "Sistem Informasi"
  },
  {
    "id": "muhammad-zaid-ats-tsabit",
    "namaLengkap": "Muhammad Zaid Ats Tsabit",
    "jurusan": "Ilmu Komputer"
  },
  {
    "id": "muhammad-rayyan-syakib-marwan",
    "namaLengkap": "MuhammadRayyanSyakibMarwan",
    "jurusan": "Ilmu Komputer"
  },
  {
    "id": "muttaqin-muzakkir",
    "namaLengkap": "Muttaqin Muzakkir",
    "jurusan": "Sistem Informasi"
  },
  {
    "id": "nabeel-muhammad",
    "namaLengkap": "Nabeel Muhammad",
    "jurusan": "Sistem Informasi"
  },
  {
    "id": "nabil-rakaiza-abror",
    "namaLengkap": "Nabil Rakaiza Abror ",
    "jurusan": "Sistem Informasi"
  },
  {
    "id": "nabil-zahid-rahman",
    "namaLengkap": "Nabil Zahid Rahman",
    "jurusan": "Sistem Informasi"
  },
  {
    "id": "nabila-maharani-putri",
    "namaLengkap": "Nabila Maharani Putri",
    "jurusan": "Sistem Informasi"
  },
  {
    "id": "nabilah-devina-mumin",
    "namaLengkap": "Nabilah Devina Mu'min",
    "jurusan": "Sistem Informasi"
  },
  {
    "id": "nabilah-devina-mumin",
    "namaLengkap": "Nabilah Devina Mu’min",
    "jurusan": "Sistem Informasi"
  },
  {
    "id": "nabilah-roslita-utami",
    "namaLengkap": "Nabilah Roslita Utami ",
    "jurusan": "Sistem Informasi"
  },
  {
    "id": "nadhif-ryan-alvaro",
    "namaLengkap": "Nadhif Ryan Alvaro",
    "jurusan": "Sistem Informasi"
  },
  {
    "id": "nadia-rahmadina-aristawati",
    "namaLengkap": "Nadia Rahmadina Aristawati",
    "jurusan": "Ilmu Komputer"
  },
  {
    "id": "nadira-aliya-nashwa",
    "namaLengkap": "Nadira Aliya Nashwa",
    "jurusan": "Sistem Informasi"
  },
  {
    "id": "nafia-levana-aulia",
    "namaLengkap": "Nafia Levana Aulia",
    "jurusan": "Sistem Informasi"
  },
  {
    "id": "nafisa-arrasyida",
    "namaLengkap": "Nafisa Arrasyida ",
    "jurusan": "Sistem Informasi"
  },
  {
    "id": "naila-nursa-krisnazulfa",
    "namaLengkap": "Naila Nursa Krisnazulfa",
    "jurusan": "Ilmu Komputer"
  },
  {
    "id": "naila-shakira-putrindari",
    "namaLengkap": "Naila Shakira Putrindari",
    "jurusan": "Sistem Informasi"
  },
  {
    "id": "naila-syarifa-yosarvi",
    "namaLengkap": "Naila Syarifa Yosarvi",
    "jurusan": "Sistem Informasi"
  },
  {
    "id": "naila-zakiyyah-effendy",
    "namaLengkap": "Naila Zakiyyah Effendy",
    "jurusan": "Sistem Informasi"
  },
  {
    "id": "naira-shafiqa-afiany",
    "namaLengkap": "Naira Shafiqa Afiany",
    "jurusan": "Sistem Informasi"
  },
  {
    "id": "najwa-zarifa",
    "namaLengkap": "Najwa Zarifa",
    "jurusan": "Sistem Informasi"
  },
  {
    "id": "najya-johara-robby",
    "namaLengkap": "Najya Johara Robby",
    "jurusan": "Sistem Informasi"
  },
  {
    "id": "namira-aulia",
    "namaLengkap": "Namira Aulia",
    "jurusan": "Sistem Informasi"
  },
  {
    "id": "nasha-zahira",
    "namaLengkap": "Nasha Zahira",
    "jurusan": "Sistem Informasi"
  },
  {
    "id": "nashwa-ghania-al-zahra",
    "namaLengkap": "Nashwa Ghania Al Zahra",
    "jurusan": "Ilmu Komputer"
  },
  {
    "id": "naurah-iradya-kurniawan",
    "namaLengkap": "Naurah Iradya Kurniawan",
    "jurusan": "Sistem Informasi"
  },
  {
    "id": "nawaetuna",
    "namaLengkap": "Nawaetuna",
    "jurusan": "Sistem Informasi"
  },
  {
    "id": "naya-kusumahayati-rachmi",
    "namaLengkap": "Naya Kusumahayati Rachmi",
    "jurusan": "Sistem Informasi"
  },
  {
    "id": "nayla-farah-nida",
    "namaLengkap": "Nayla Farah Nida ",
    "jurusan": "Ilmu Komputer"
  },
  {
    "id": "nelil-amaani",
    "namaLengkap": "Nelil Amaani",
    "jurusan": "Sistem Informasi"
  },
  {
    "id": "nevin-thang",
    "namaLengkap": "Nevin Thang",
    "jurusan": "Sistem Informasi"
  },
  {
    "id": "nisa-najla-hanina-hasanah",
    "namaLengkap": "Nisa Najla Hanina Hasanah",
    "jurusan": "Sistem Informasi"
  },
  {
    "id": "nisrina-annaisha-sarnadi",
    "namaLengkap": "Nisrina Annaisha Sarnadi ",
    "jurusan": "Ilmu Komputer"
  },
  {
    "id": "nisrina-kamilya-nisyya",
    "namaLengkap": "Nisrina Kamilya Nisyya",
    "jurusan": "Sistem Informasi"
  },
  {
    "id": "nobel-julian-bintang",
    "namaLengkap": "Nobel Julian Bintang",
    "jurusan": "Ilmu Komputer"
  },
  {
    "id": "nur-alya-khairina",
    "namaLengkap": "Nur Alya Khairina ",
    "jurusan": "Sistem Informasi"
  },
  {
    "id": "nur-khoirunnisa-salsabila",
    "namaLengkap": "Nur Khoirunnisa Salsabila",
    "jurusan": "Sistem Informasi"
  },
  {
    "id": "olav-dendy-christian-manullang",
    "namaLengkap": "Olav Dendy Christian Manullang",
    "jurusan": "Sistem Informasi"
  },
  {
    "id": "omar-ahmad-bumi-ngabehi",
    "namaLengkap": "Omar Ahmad Bumi Ngabehi",
    "jurusan": "Ilmu Komputer"
  },
  {
    "id": "orlando-devito",
    "namaLengkap": "Orlando Devito",
    "jurusan": "Sistem Informasi"
  },
  {
    "id": "oscar-ryanda",
    "namaLengkap": "Oscar Ryanda",
    "jurusan": "Sistem Informasi"
  },
  {
    "id": "paima-ishak-melkisedek-purba",
    "namaLengkap": "Paima Ishak Melkisedek Purba",
    "jurusan": "Ilmu Komputer"
  },
  {
    "id": "palastha-zhorif-kawiswara",
    "namaLengkap": "Palastha Zhorif Kawiswara",
    "jurusan": "Sistem Informasi"
  },
  {
    "id": "pascal-hafidz-fajri",
    "namaLengkap": "Pascal Hafidz Fajri ",
    "jurusan": "Ilmu Komputer"
  },
  {
    "id": "patricia-gloria-sujatmoko-silaban",
    "namaLengkap": "Patricia Gloria Sujatmoko Silaban",
    "jurusan": "Sistem Informasi"
  },
  {
    "id": "patricia-herningtyas",
    "namaLengkap": "Patricia Herningtyas",
    "jurusan": "Ilmu Komputer"
  },
  {
    "id": "peter-putra-lesmana",
    "namaLengkap": "Peter Putra Lesmana",
    "jurusan": "Ilmu Komputer"
  },
  {
    "id": "philip-halomoan-sampenta-manurung",
    "namaLengkap": "Philip Halomoan Sampenta Manurung",
    "jurusan": "Sistem Informasi"
  },
  {
    "id": "pradipta-wachyu-aditama",
    "namaLengkap": "Pradipta Wachyu Aditama",
    "jurusan": "Ilmu Komputer"
  },
  {
    "id": "priscilla-natanael-surjanto",
    "namaLengkap": "Priscilla Natanael Surjanto",
    "jurusan": "Ilmu Komputer"
  },
  {
    "id": "priyapta-naufal-sudrajat",
    "namaLengkap": "Priyapta Naufal Sudrajat",
    "jurusan": "Ilmu Komputer"
  },
  {
    "id": "raden-ahmad-yasin-mahendra",
    "namaLengkap": "Raden Ahmad Yasin Mahendra",
    "jurusan": "Ilmu Komputer"
  },
  {
    "id": "rafansya-daryltama-santoso",
    "namaLengkap": "Rafansya Daryltama Santoso",
    "jurusan": "Sistem Informasi"
  },
  {
    "id": "raffi-dary-hibban",
    "namaLengkap": "Raffi Dary Hibban",
    "jurusan": "Sistem Informasi"
  },
  {
    "id": "rafie-asadel-tarigan",
    "namaLengkap": "Rafie Asadel Tarigan",
    "jurusan": "Sistem Informasi"
  },
  {
    "id": "rafif-sulaiman-dirvesa",
    "namaLengkap": "Rafif Sulaiman Dirvesa",
    "jurusan": "Sistem Informasi"
  },
  {
    "id": "ragnall-muhammad-al-fath",
    "namaLengkap": "Ragnall Muhammad Al Fath",
    "jurusan": "Ilmu Komputer"
  },
  {
    "id": "rahardi-salim",
    "namaLengkap": "Rahardi Salim",
    "jurusan": "Ilmu Komputer"
  },
  {
    "id": "rahma-dwi-maghfira",
    "namaLengkap": "Rahma Dwi Maghfira",
    "jurusan": "Sistem Informasi"
  },
  {
    "id": "raihan-akbar",
    "namaLengkap": "Raihan akbar",
    "jurusan": "Ilmu Komputer"
  },
  {
    "id": "raisa-sakila",
    "namaLengkap": "Raisa Sakila",
    "jurusan": "Sistem Informasi"
  },
  {
    "id": "rajendra-rifqi-baskara",
    "namaLengkap": "Rajendra Rifqi Baskara",
    "jurusan": "Sistem Informasi"
  },
  {
    "id": "rakabima-ghaniendra-rusdianto",
    "namaLengkap": "Rakabima Ghaniendra Rusdianto",
    "jurusan": "Ilmu Komputer"
  },
  {
    "id": "rama-aditya-rifki-harmono",
    "namaLengkap": "Rama Aditya Rifki Harmono",
    "jurusan": "Sistem Informasi"
  },
  {
    "id": "ramy-ardya-ramadhan",
    "namaLengkap": "Ramy Ardya Ramadhan",
    "jurusan": "Ilmu Komputer"
  },
  {
    "id": "rania-berliana",
    "namaLengkap": "Rania Berliana",
    "jurusan": "Sistem Informasi"
  },
  {
    "id": "rayhan-alviandi",
    "namaLengkap": "Rayhan Alviandi",
    "jurusan": "Sistem Informasi"
  },
  {
    "id": "rayhan-syahdira-putra",
    "namaLengkap": "Rayhan Syahdira Putra",
    "jurusan": "Ilmu Komputer"
  },
  {
    "id": "rayienda-hasmaradana-najlamahsa",
    "namaLengkap": "Rayienda Hasmaradana Najlamahsa ",
    "jurusan": "Ilmu Komputer KKI"
  },
  {
    "id": "raysha-reifika-ryzki",
    "namaLengkap": "Raysha Reifika Ryzki",
    "jurusan": "Sistem Informasi"
  },
  {
    "id": "rebecca-zaneta-octoria-hutajulu",
    "namaLengkap": "Rebecca Zaneta Octoria Hutajulu",
    "jurusan": "Ilmu Komputer"
  },
  {
    "id": "refalino-shahzada-ghassani",
    "namaLengkap": "Refalino Shahzada Ghassani",
    "jurusan": "Ilmu Komputer"
  },
  {
    "id": "regina-meilani-aruan",
    "namaLengkap": "Regina Meilani Aruan",
    "jurusan": "Sistem Informasi"
  },
  {
    "id": "reinaldi-shahlangga-dalius",
    "namaLengkap": "Reinaldi Shahlangga Dalius",
    "jurusan": "Sistem Informasi"
  },
  {
    "id": "reyvano-mario-sianturi",
    "namaLengkap": "Reyvano Mario Sianturi",
    "jurusan": "Sistem Informasi"
  },
  {
    "id": "ridya-azizah-khayyira-mumtaz",
    "namaLengkap": "Ridya Azizah Khayyira Mumtaz",
    "jurusan": "Sistem Informasi"
  },
  {
    "id": "rifqisyandi-khairurrizal",
    "namaLengkap": "Rifqisyandi Khairurrizal",
    "jurusan": "Ilmu Komputer"
  },
  {
    "id": "rizki-amani-hasanah",
    "namaLengkap": "Rizki Amani Hasanah",
    "jurusan": "Sistem Informasi"
  },
  {
    "id": "rizki-hidayatul-laeli",
    "namaLengkap": "Rizki Hidayatul Laeli",
    "jurusan": "Sistem Informasi"
  },
  {
    "id": "rizqya-az-zahra-putri",
    "namaLengkap": "Rizqya Az Zahra Putri",
    "jurusan": "Ilmu Komputer"
  },
  {
    "id": "rogerio-geraldo-wibhowo",
    "namaLengkap": "Rogerio Geraldo Wibhowo",
    "jurusan": "Sistem Informasi"
  },
  {
    "id": "rosanne-valerie",
    "namaLengkap": "Rosanne Valerie ",
    "jurusan": "Sistem Informasi"
  },
  {
    "id": "safira-salma-humaira",
    "namaLengkap": "Safira Salma Humaira",
    "jurusan": "Sistem Informasi"
  },
  {
    "id": "salomo-immanuel-putra",
    "namaLengkap": "Salomo Immanuel Putra",
    "jurusan": "Sistem Informasi"
  },
  {
    "id": "salsabila-arumdapta",
    "namaLengkap": "Salsabila Arumdapta",
    "jurusan": "Sistem Informasi"
  },
  {
    "id": "salsabila-caturizky-farindarmawan",
    "namaLengkap": "Salsabila Caturizky Farindarmawan ",
    "jurusan": "Sistem Informasi"
  },
  {
    "id": "samuel-sebastian-sibarani",
    "namaLengkap": "Samuel Sebastian Sibarani",
    "jurusan": "Sistem Informasi"
  },
  {
    "id": "samuella-putri-nadia-pauntu",
    "namaLengkap": "Samuella Putri Nadia Pauntu",
    "jurusan": "Ilmu Komputer KKI"
  },
  {
    "id": "sarah-saphira-setiawan",
    "namaLengkap": "Sarah Saphira Setiawan",
    "jurusan": "Sistem Informasi"
  },
  {
    "id": "sayyid-thariq-gilang-muttaqien",
    "namaLengkap": "Sayyid Thariq Gilang Muttaqien",
    "jurusan": "Sistem Informasi"
  },
  {
    "id": "sean-farrel-japardhana",
    "namaLengkap": "Sean Farrel Japardhana",
    "jurusan": "Ilmu Komputer"
  },
  {
    "id": "serafina-nala-putri-setiawan",
    "namaLengkap": "Serafina Nala Putri Setiawan",
    "jurusan": "Ilmu Komputer KKI"
  },
  {
    "id": "sezza-auraghaniya",
    "namaLengkap": "Sezza Auraghaniya ",
    "jurusan": "Sistem Informasi"
  },
  {
    "id": "shabrina-aulia-kinanti",
    "namaLengkap": "Shabrina Aulia Kinanti",
    "jurusan": "Sistem Informasi"
  },
  {
    "id": "shafa-amira-azka",
    "namaLengkap": "Shafa Amira Azka ",
    "jurusan": "Sistem Informasi"
  },
  {
    "id": "shaine-glorvina-mathea",
    "namaLengkap": "Shaine Glorvina Mathea",
    "jurusan": "Sistem Informasi"
  },
  {
    "id": "shalya-naura-lionita",
    "namaLengkap": "Shalya Naura Lionita",
    "jurusan": "Sistem Informasi"
  },
  {
    "id": "shane-michael-tanata-tendy",
    "namaLengkap": "Shane Michael Tanata Tendy",
    "jurusan": "Ilmu Komputer"
  },
  {
    "id": "shaney-zoya-fiandi",
    "namaLengkap": "Shaney Zoya Fiandi",
    "jurusan": "Sistem Informasi"
  },
  {
    "id": "shintia-dharma-shanty",
    "namaLengkap": "Shintia Dharma Shanty",
    "jurusan": "Sistem Informasi"
  },
  {
    "id": "simforianus-jonathan-flonas-harefa",
    "namaLengkap": "Simforianus Jonathan Flonas Harefa",
    "jurusan": "Ilmu Komputer"
  },
  {
    "id": "siti-shofi-nadhifa",
    "namaLengkap": "Siti Shofi Nadhifa",
    "jurusan": "Ilmu Komputer"
  },
  {
    "id": "stefanus-tan-jaya",
    "namaLengkap": "Stefanus Tan Jaya",
    "jurusan": "Ilmu Komputer"
  },
  {
    "id": "steven-paska-haryanto",
    "namaLengkap": "Steven Paska Haryanto",
    "jurusan": "Sistem Informasi"
  },
  {
    "id": "steven-setiawan",
    "namaLengkap": "Steven Setiawan",
    "jurusan": "Ilmu Komputer"
  },
  {
    "id": "sultan-ibnu-mansiz",
    "namaLengkap": "Sultan Ibnu Mansiz",
    "jurusan": "Ilmu Komputer"
  },
  {
    "id": "sulthan-adrin-pasha-siregar",
    "namaLengkap": "Sulthan Adrin Pasha Siregar",
    "jurusan": "Sistem Informasi"
  },
  {
    "id": "suriya-sayud",
    "namaLengkap": "Suriya Sayud",
    "jurusan": "Ilmu Komputer"
  },
  {
    "id": "syahirah-putri-aisyah",
    "namaLengkap": "Syahirah Putri Aisyah",
    "jurusan": "Sistem Informasi"
  },
  {
    "id": "syauqi-muhammad-yasman",
    "namaLengkap": "Syauqi Muhammad Yasman",
    "jurusan": "Ilmu Komputer"
  },
  {
    "id": "syifa-ananda-widyati",
    "namaLengkap": "Syifa Ananda Widyati",
    "jurusan": "Ilmu Komputer KKI"
  },
  {
    "id": "talitha-zenda-shakira",
    "namaLengkap": "Talitha Zenda Shakira",
    "jurusan": "Sistem Informasi"
  },
  {
    "id": "tarissa-mutia-andini",
    "namaLengkap": "Tarissa Mutia Andini",
    "jurusan": "Sistem Informasi"
  },
  {
    "id": "theo-ananda-lemuel",
    "namaLengkap": "Theo Ananda Lemuel",
    "jurusan": "Sistem Informasi"
  },
  {
    "id": "theodore-kevin-himawan",
    "namaLengkap": "Theodore Kevin Himawan",
    "jurusan": "Ilmu Komputer"
  },
  {
    "id": "theresia-tarianingsih",
    "namaLengkap": "Theresia Tarianingsih",
    "jurusan": "Sistem Informasi"
  },
  {
    "id": "thorbert-anson-shi",
    "namaLengkap": "Thorbert Anson Shi",
    "jurusan": "Ilmu Komputer"
  },
  {
    "id": "trias-fahri-naufal",
    "namaLengkap": "Trias Fahri Naufal",
    "jurusan": "Sistem Informasi"
  },
  {
    "id": "tristan-agra-yudhistira",
    "namaLengkap": "Tristan Agra Yudhistira ",
    "jurusan": "Ilmu Komputer"
  },
  {
    "id": "utandra-nur-ahmad-jais",
    "namaLengkap": "Utandra Nur Ahmad Jais",
    "jurusan": "Ilmu Komputer"
  },
  {
    "id": "valentino-kim-fernando",
    "namaLengkap": "Valentino Kim Fernando",
    "jurusan": "Ilmu Komputer"
  },
  {
    "id": "valentino-vieri-zhuo",
    "namaLengkap": "Valentino Vieri Zhuo",
    "jurusan": "Ilmu Komputer"
  },
  {
    "id": "valiza-nadya-jatikansha",
    "namaLengkap": "Valiza Nadya Jatikansha",
    "jurusan": "Sistem Informasi"
  },
  {
    "id": "vian-farizan-narenra",
    "namaLengkap": "Vian Farizan Narenra",
    "jurusan": "Sistem Informasi"
  },
  {
    "id": "vico-winner-sebastian-aritonang",
    "namaLengkap": "Vico Winner Sebastian Aritonang",
    "jurusan": "Sistem Informasi"
  },
  {
    "id": "vincent-davis-leonard-tjoeng",
    "namaLengkap": "Vincent Davis Leonard Tjoeng",
    "jurusan": "Ilmu Komputer"
  },
  {
    "id": "vissuta-gunawan-lim",
    "namaLengkap": "Vissuta Gunawan Lim ",
    "jurusan": "Ilmu Komputer"
  },
  {
    "id": "waode-inaya-diza-mainah",
    "namaLengkap": "Waode Inaya Diza Ma'inah",
    "jurusan": "Ilmu Komputer"
  },
  {
    "id": "wida-putri-kinasih",
    "namaLengkap": "Wida Putri Kinasih",
    "jurusan": "Ilmu Komputer"
  },
  {
    "id": "widya-mutia-ichsan",
    "namaLengkap": "Widya Mutia Ichsan ",
    "jurusan": "Sistem Informasi"
  },
  {
    "id": "wildan-athallah-raharja",
    "namaLengkap": "Wildan Athallah Raharja",
    "jurusan": "Ilmu Komputer"
  },
  {
    "id": "william-alexander",
    "namaLengkap": "William Alexander",
    "jurusan": "Ilmu Komputer"
  },
  {
    "id": "william-matthew-saputra",
    "namaLengkap": "William Matthew Saputra",
    "jurusan": "Sistem Informasi"
  },
  {
    "id": "william-samuel-mulya",
    "namaLengkap": "William Samuel Mulya",
    "jurusan": "Ilmu Komputer KKI"
  },
  {
    "id": "wirya-dharma-kurnia",
    "namaLengkap": "Wirya Dharma Kurnia",
    "jurusan": "Ilmu Komputer"
  },
  {
    "id": "wisnu-nugroho",
    "namaLengkap": "Wisnu Nugroho ",
    "jurusan": "Ilmu Komputer"
  },
  {
    "id": "yemima-clara-nainggolan",
    "namaLengkap": "Yemima Clara Nainggolan",
    "jurusan": "Sistem Informasi"
  },
  {
    "id": "yeshua-marco-gracia-manurung",
    "namaLengkap": "Yeshua Marco Gracia Manurung",
    "jurusan": "Sistem Informasi"
  },
  {
    "id": "yose-yehezkiel-maranata",
    "namaLengkap": "Yose Yehezkiel Maranata ",
    "jurusan": "Ilmu Komputer"
  },
  {
    "id": "yosia-joseph-chandra",
    "namaLengkap": "Yosia Joseph Chandra",
    "jurusan": "Ilmu Komputer"
  },
  {
    "id": "yovan-raju",
    "namaLengkap": "Yovan Raju",
    "jurusan": "Sistem Informasi"
  },
  {
    "id": "yudayana-arif-prasojo",
    "namaLengkap": "Yudayana Arif Prasojo",
    "jurusan": "Ilmu Komputer"
  },
  {
    "id": "zakiy-makarim-iskandar-daulay",
    "namaLengkap": "Zakiy Makarim Iskandar Daulay",
    "jurusan": "Ilmu Komputer KKI"
  },
  {
    "id": "zillan-ahmad-ryandi",
    "namaLengkap": "Zillan ahmad ryandi",
    "jurusan": "Sistem Informasi"
  },
  {
    "id": "zufar-romli-amri",
    "namaLengkap": "Zufar Romli Amri ",
    "jurusan": "Ilmu Komputer"
  }
]